potyk_doc/__init__.py
potyk_doc/content_disposition.py
potyk_doc/docx.py
potyk_doc/file.py
potyk_doc/models.py
potyk_doc/money.py
potyk_doc/pdf.py
potyk_doc/translation/__init__.py
potyk_doc/translation/_num2t4ru.py
potyk_doc/translation/case.py
potyk_doc/translation/dt.py
potyk_doc/translation/money.py
potyk_doc/translation/number.py
potyk_doc/xlsx.py
potyk_doc/zip_.py
potyk_doc-0.8.4.dist-info/WHEEL
potyk_doc-0.8.4.dist-info/METADATA
potyk_doc-0.8.4.dist-info/RECORD
