Metadata-Version: 2.1
Name: potyk-doc
Version: 0.8.4
Summary: 
Author: potykion
Author-email: potykion@gmail.com
Requires-Python: >=3.9,<4.0
Classifier: Programming Language :: Python :: 3
Classifier: Programming Language :: Python :: 3.9
Requires-Dist: PyPDF2 (>=3.0.0,<4.0.0)
Requires-Dist: docxtpl (>=0.16.4,<0.17.0)
Requires-Dist: jinja2xlsx (>=1,<2)
Requires-Dist: pdfkit (>=1.0.0,<2.0.0)
Requires-Dist: potyk-lib (>=0.6,<0.7)
